repocutter/__init__.py
repocutter/__main__.py
repocutter/_main.py
repocutter/_version.py
repocutter/py.typed
repocutter-0.6.2.dist-info/LICENSE
repocutter-0.6.2.dist-info/METADATA
repocutter-0.6.2.dist-info/WHEEL
repocutter-0.6.2.dist-info/entry_points.txt
repocutter-0.6.2.dist-info/RECORD
