Metadata-Version: 2.1
Name: repocutter
Version: 0.6.2
Summary: Checkout repos to current cookiecutter config
Home-page: https://pypi.org/project/repocutter/
License: MIT
Keywords: config,cookiecutter,jinja2,repo,template
Author: jshwi
Author-email: stephen@jshwisolutions.com
Maintainer: jshwi
Maintainer-email: stephen@jshwisolutions.com
Requires-Python: >=3.8,<4.0
Classifier: License :: OSI Approved :: MIT License
Classifier: Programming Language :: Python :: 3
Classifier: Programming Language :: Python :: 3.8
Classifier: Programming Language :: Python :: 3.9
Classifier: Programming Language :: Python :: 3.10
Classifier: Programming Language :: Python :: 3.11
Requires-Dist: appdirs (>=1.4.4,<2.0.0)
Requires-Dist: arcon (>=0.2,<0.4)
Requires-Dist: checksumdir (>=1.2.0,<2.0.0)
Requires-Dist: cookiecutter (>=2.1.1,<3.0.0)
Requires-Dist: gitspy (>=0.3.0,<0.4.0)
Requires-Dist: object-colors (>=2.2.0,<3.0.0)
Requires-Dist: tomli (>=2.0.1,<3.0.0)
Project-URL: Documentation, https://repocutter.readthedocs.io/en/latest
Project-URL: Repository, https://github.com/jshwi/repocutter
